satellitescraper/__init__.py
satellitescraper/file_size.py
satellitescraper/map_fetch.py
satellitescraper/sanity_checker.py
satellitescraper/satellitescraper.py
satellitescraper/tiles_sticher.py
satellitescraper-0.2.0.dist-info/LICENSE
satellitescraper-0.2.0.dist-info/METADATA
satellitescraper-0.2.0.dist-info/WHEEL
satellitescraper-0.2.0.dist-info/top_level.txt
satellitescraper-0.2.0.dist-info/RECORD
