Metadata-Version: 2.1
Name: satellitescraper
Version: 0.2.0
Summary: Python Package for Scraping Sattelite Image Data
Home-page: https://github.com/Mostafamabrok/longitude
Author: Mostafa Mabrok
Author-email: mostafa.m.mabrok@gmail.com
Classifier: Programming Language :: Python :: 3
Classifier: License :: OSI Approved :: MIT License
Classifier: Operating System :: OS Independent
License-File: LICENSE
Requires-Dist: certifi
Requires-Dist: chardet
Requires-Dist: chromedriver-autoinstaller
Requires-Dist: idna
Requires-Dist: numpy
Requires-Dist: requests
Requires-Dist: selenium
Requires-Dist: tqdm
Requires-Dist: urllib3
Requires-Dist: opencv-python
Requires-Dist: webdriver-manager
